qsft/BeliefPropagation.py
qsft/ReedSolomon.py
qsft/__init__.py
qsft/input_signal.py
qsft/input_signal_subsampled.py
qsft/lasso.py
qsft/parallel_tests.py
qsft/peel.py
qsft/query.py
qsft/reconstruct.py
qsft/test_helper.py
qsft/utils.py
qsft/wrapper.py
qsft-0.0.2.dist-info/METADATA
qsft-0.0.2.dist-info/WHEEL
qsft-0.0.2.dist-info/licenses/LICENSE
qsft-0.0.2.dist-info/RECORD
