Metadata-Version: 2.3
Name: qsft
Version: 0.0.2
Summary: Efficiently computing sparse Fourier transforms of functions
Project-URL: Homepage, https://github.com/basics-lab/qsft
Author-email: Yigit Efe Erginbas <erginbas@berkeley.edu>, Justin Kang <justin_kang@berkeley.edu>
License-File: LICENSE
Classifier: License :: OSI Approved :: MIT License
Classifier: Operating System :: OS Independent
Classifier: Programming Language :: Python :: 3
Requires-Python: >=3.8
Requires-Dist: galois==0.1.1
Requires-Dist: multiprocess
Requires-Dist: numpy>1.18
Requires-Dist: scipy
Requires-Dist: tqdm
